pynorm/__init__.py
pynorm/client.py
pynorm/exceptions.py
pynorm/models.py
pynorm/types.py
pynorm_sdk-0.1.0.dist-info/METADATA
pynorm_sdk-0.1.0.dist-info/WHEEL
pynorm_sdk-0.1.0.dist-info/licenses/LICENSE
pynorm_sdk-0.1.0.dist-info/RECORD
