Metadata-Version: 2.4
Name: pynorm-sdk
Version: 0.1.0
Summary: A modern, async Python SDK for the RxNorm API that provides comprehensive access to drug information and terminology
Project-URL: Homepage, https://github.com/akauper/pynorm
Project-URL: Repository, https://github.com/akauper/pynorm
Project-URL: Bug Tracker, https://github.com/akauper/pynorm/issues
Project-URL: Documentation, https://github.com/akauper/pynorm#readme
Author-email: Adam Kauper <akauper@gmail.com>
Maintainer-email: Adam Kauper <akauper@gmail.com>
License-Expression: MIT
License-File: LICENSE
Keywords: api,async,drugs,healthcare,medical,rxnorm,sdk
Classifier: Development Status :: 4 - Beta
Classifier: Framework :: AsyncIO
Classifier: Intended Audience :: Developers
Classifier: Intended Audience :: Healthcare Industry
Classifier: License :: OSI Approved :: MIT License
Classifier: Programming Language :: Python :: 3
Classifier: Programming Language :: Python :: 3.12
Classifier: Topic :: Scientific/Engineering :: Medical Science Apps.
Classifier: Topic :: Software Development :: Libraries :: Python Modules
Classifier: Typing :: Typed
Requires-Python: >=3.12
Requires-Dist: aiohttp>=3.12.15
Requires-Dist: pydantic-settings>=2.10.1
Requires-Dist: pydantic>=2.11.7
